[{"TerrainParameterObjectCount":[10,10],"ObjectListPath":["Assets/Resources/Content/Tree.prefab","Assets/Resources/Content/Tree.prefab"],"ObjectListCount":2,"Name":"Mnt","ParameterBoundry":1.0,"TemperatureParameterBoundry":1.0,"MoistureParameterBoundry":0.0,"TerrainColorVector":{"x":0.385947,"y":0.407196075,"z":0.46226418,"w":1.0,"normalized":{"x":0.312177628,"y":0.3293652,"z":0.373907655,"w":0.808861434,"magnitude":1.0,"sqrMagnitude":1.0},"magnitude":1.23630571,"sqrMagnitude":1.52845192},"TexturePathSpring":"Assets/Resources/UpdatedTextures/RockDark004_COL_VAR2_6K copy.jpg","TexturePathSummer":"Assets/Resources/UpdatedTextures/summer_texture_devel.jpg","TexturePathAutumn":"Assets/Resources/UpdatedTextures/autumn_texture_devel.jpg","TexturePathWinter":"Assets/Resources/UpdatedTextures/winter_texture_devel.jpg"},{"TerrainParameterObjectCount":[5],"ObjectListPath":["Assets/Resources/Content/Tree.prefab"],"ObjectListCount":1,"Name":"TropicalSeasonalForest","ParameterBoundry":0.4,"TemperatureParameterBoundry":0.7,"MoistureParameterBoundry":0.9,"TerrainColorVector":{"x":0.7122077,"y":0.9150943,"z":0.0561142974,"w":1.0,"normalized":{"x":0.46481204,"y":0.5972231,"z":0.0366221853,"w":0.6526356,"magnitude":1.0,"sqrMagnitude":1.0},"magnitude":1.53224874,"sqrMagnitude":2.34778619},"TexturePathSpring":"Assets/Resources/Ground textures pack/Grass & dead leafs 01/diffuse.tga","TexturePathSummer":"Assets/Resources/UpdatedTextures/summer_texture_devel.jpg","TexturePathAutumn":"Assets/Resources/UpdatedTextures/autumn_texture_devel.jpg","TexturePathWinter":"Assets/Resources/UpdatedTextures/winter_texture_devel.jpg"},{"TerrainParameterObjectCount":[13],"ObjectListPath":["Assets/Resources/Content/Tree.prefab"],"ObjectListCount":1,"Name":"BorealForest","ParameterBoundry":0.5,"TemperatureParameterBoundry":0.3,"MoistureParameterBoundry":0.8,"TerrainColorVector":{"x":0.240308866,"y":0.3679245,"z":0.0,"w":1.0,"normalized":{"x":0.220002845,"y":0.336835027,"z":0.0,"w":0.915500343,"normalized":{"x":0.22000286,"y":0.336835057,"z":0.0,"w":0.9155004,"magnitude":1.0,"sqrMagnitude":1.00000012},"magnitude":0.99999994,"sqrMagnitude":0.99999994},"magnitude":1.09229887,"sqrMagnitude":1.19311678},"TexturePathSpring":"Assets/Resources/Ground textures pack/Grass & rocks/diffuse.tga","TexturePathSummer":"Assets/Resources/UpdatedTextures/summer_texture_devel.jpg","TexturePathAutumn":"Assets/Resources/UpdatedTextures/autumn_texture_devel.jpg","TexturePathWinter":"Assets/Resources/UpdatedTextures/winter_texture_devel.jpg"},{"TerrainParameterObjectCount":[4],"ObjectListPath":["Assets/Resources/Content/Tree.prefab"],"ObjectListCount":1,"Name":"Woodland","ParameterBoundry":0.2,"TemperatureParameterBoundry":0.6,"MoistureParameterBoundry":0.63,"TerrainColorVector":{"x":0.4716981,"y":0.3138042,"z":0.0,"w":1.0,"normalized":{"x":0.410409421,"y":0.273031,"z":0.0,"w":0.870067954,"magnitude":1.0,"sqrMagnitude":1.00000012},"magnitude":1.1493355,"sqrMagnitude":1.3209722},"TexturePathSpring":"Assets/Resources/Ground textures pack/Ground & moss/diffuse.tga","TexturePathSummer":"Assets/Resources/UpdatedTextures/summer_texture_devel.jpg","TexturePathAutumn":"Assets/Resources/UpdatedTextures/autumn_texture_devel.jpg","TexturePathWinter":"Assets/Resources/UpdatedTextures/winter_texture_devel.jpg"},{"TerrainParameterObjectCount":[11],"ObjectListPath":["Assets/Resources/Content/Tree.prefab"],"ObjectListCount":1,"Name":"Shrubland","ParameterBoundry":0.8,"TemperatureParameterBoundry":0.7,"MoistureParameterBoundry":0.9,"TerrainColorVector":{"x":0.7830189,"y":0.6910965,"z":0.542942345,"w":1.0,"normalized":{"x":0.50696826,"y":0.447452784,"z":0.3515299,"w":0.6474534,"magnitude":1.0,"sqrMagnitude":1.0},"magnitude":1.54451263,"sqrMagnitude":2.38551927},"TexturePathSpring":"Assets/Resources/Ground textures pack/Grass 01/diffuse.tga","TexturePathSummer":"Assets/Resources/UpdatedTextures/summer_texture_devel.jpg","TexturePathAutumn":"Assets/Resources/UpdatedTextures/autumn_texture_devel.jpg","TexturePathWinter":"Assets/Resources/UpdatedTextures/winter_texture_devel.jpg"},{"TerrainParameterObjectCount":[5],"ObjectListPath":["Assets/Resources/Content/Tree.prefab"],"ObjectListCount":1,"Name":"TemperateSeasonalForest","ParameterBoundry":0.8,"TemperatureParameterBoundry":0.1,"MoistureParameterBoundry":0.9,"TerrainColorVector":{"x":0.6099867,"y":1.0,"z":0.5990566,"w":1.0,"normalized":{"x":0.369116366,"y":0.60512197,"z":0.3625023,"w":0.60512197,"magnitude":1.0,"sqrMagnitude":1.0},"magnitude":1.6525594,"sqrMagnitude":2.7309525},"TexturePathSpring":"Assets/Resources/Ground textures pack/Grass 06/diffuse.tga","TexturePathSummer":"Assets/Resources/UpdatedTextures/summer_texture_devel.jpg","TexturePathAutumn":"Assets/Resources/UpdatedTextures/autumn_texture_devel.jpg","TexturePathWinter":"Assets/Resources/UpdatedTextures/winter_texture_devel.jpg"},{"TerrainParameterObjectCount":[6],"ObjectListPath":["Assets/Resources/Content/Tree.prefab"],"ObjectListCount":1,"Name":"Water","ParameterBoundry":1.0,"TemperatureParameterBoundry":1.0,"MoistureParameterBoundry":1.0,"TerrainColorVector":{"x":0.136792481,"y":0.204598963,"z":1.0,"w":1.0,"normalized":{"x":0.0952945948,"y":0.142531037,"z":0.6966362,"w":0.6966362,"magnitude":1.0,"sqrMagnitude":1.00000012},"magnitude":1.43546951,"sqrMagnitude":2.06057286},"TexturePathSpring":"Assets/Resources/UpdatedTextures/GroundSand003_COL_VAR1_6K copy.jpg","TexturePathSummer":"Assets/Resources/UpdatedTextures/summer_texture_devel.jpg","TexturePathAutumn":"Assets/Resources/UpdatedTextures/autumn_texture_devel.jpg","TexturePathWinter":"Assets/Resources/UpdatedTextures/winter_texture_devel.jpg"}]